pyarabic/__init__.py
pyarabic/arabrepr.py
pyarabic/araby.py
pyarabic/araby_const.py
pyarabic/kalima.py
pyarabic/named.py
pyarabic/named_const.py
pyarabic/normalize.py
pyarabic/number.py
pyarabic/number_const.py
pyarabic/propernouns.py
pyarabic/stack.py
pyarabic/trans.py
pyarabic/unshape.py
pyarabic/util.py
PyArabic-0.6.13.dist-info/LICENSE
PyArabic-0.6.13.dist-info/METADATA
PyArabic-0.6.13.dist-info/WHEEL
PyArabic-0.6.13.dist-info/top_level.txt
PyArabic-0.6.13.dist-info/RECORD
