Metadata-Version: 2.1
Name: PyArabic
Version: 0.6.13
Summary: Arabic text tools for Python
Home-page: http://pyarabic.sourceforge.net/
Author: Taha Zerrouki
Author-email: taha_zerrouki@hotmail.com
License: GPL
Platform: UNKNOWN
Classifier: Development Status :: 5 - Production/Stable
Classifier: Natural Language :: Arabic
Classifier: Intended Audience :: Developers
Classifier: Operating System :: OS Independent
Classifier: Programming Language :: Python
Classifier: Programming Language :: Python :: 2
Classifier: Programming Language :: Python :: 3
Classifier: Topic :: Text Processing :: Linguistic
Requires-Dist: six (>=1.14.0)
